README.txt
iscompatible.py
setup.py
iscompatible.egg-info/PKG-INFO
iscompatible.egg-info/SOURCES.txt
iscompatible.egg-info/dependency_links.txt
iscompatible.egg-info/not-zip-safe
iscompatible.egg-info/top_level.txt