Metadata-Version: 1.1
Name: iscompatible
Version: 0.1.0
Summary: Python versioning with requirements.txt syntax
Home-page: https://github.com/mottosso/iscompatible
Author: Marcus Ottosson
Author-email: marcus@abstractfactory.com
License: The MIT License (MIT)
